{
"skeleton": { "hash": "u0r2TLKPEVS0EE+BcO2OgvSSpCI", "spine": "3.0.08", "width": 326.77, "height": 313, "images": "" },
"bones": [
	{ "name": "root" },
	{ "name": "bone8", "parent": "root", "x": -82.61 },
	{ "name": "bone9", "parent": "bone8", "x": -15.65, "y": 41.61 },
	{ "name": "bone7", "parent": "bone8", "length": 104.13, "x": 40.72, "y": 17.02 },
	{ "name": "bone6", "parent": "bone7", "x": 52.29, "y": -51.68 },
	{ "name": "bone5", "parent": "bone7", "x": 24.22, "y": -31.57 },
	{ "name": "bone4", "parent": "bone7", "x": -0.49, "y": -15.23 },
	{ "name": "bone3", "parent": "bone7", "x": 19.19, "y": 5.71 },
	{ "name": "bone2", "parent": "bone7", "x": 40.14, "y": 19.54 },
	{ "name": "bone", "parent": "bone8", "x": -42.19, "y": 43.71 }
],
"slots": [
	{ "name": "1/1", "bone": "bone2", "attachment": "1/1" },
	{ "name": "1/2", "bone": "bone3", "attachment": "1/1" },
	{ "name": "1/3", "bone": "bone4", "attachment": "1/1" },
	{ "name": "1/000000", "bone": "bone" },
	{ "name": "1/4", "bone": "bone5", "attachment": "1/1" },
	{ "name": "1/5", "bone": "bone6", "attachment": "1/1" },
	{ "name": "1/1/0001", "bone": "bone9", "attachment": "1/1/0004" }
],
"skins": {
	"default": {
		"1/000000": {
			"1/000000": { "x": 13.5, "y": 1.99, "width": 393, "height": 206 },
			"1/000002": { "x": 13.5, "y": 1.99, "width": 393, "height": 206 },
			"1/000004": { "x": 13.5, "y": 1.99, "width": 393, "height": 206 },
			"1/000006": { "x": 13.5, "y": 1.99, "width": 393, "height": 206 },
			"1/000008": { "x": 13.5, "y": 1.99, "width": 393, "height": 206 },
			"1/000010": { "x": 13.5, "y": 1.99, "width": 393, "height": 206 },
			"1/000012": { "x": 13.5, "y": 1.99, "width": 393, "height": 206 },
			"1/000014": { "x": 13.5, "y": 1.99, "width": 393, "height": 206 },
			"1/000016": { "x": 13.5, "y": 1.99, "width": 393, "height": 206 }
		},
		"1/1": {
			"1/1": { "x": 1.34, "y": 29.66, "width": 129, "height": 82 }
		},
		"1/1/0001": {
			"1/1/0001": { "x": 5.25, "y": 13.12, "width": 315, "height": 313 },
			"1/1/0002": { "x": 5.25, "y": 13.12, "width": 315, "height": 313 },
			"1/1/0003": { "x": 5.25, "y": 13.12, "width": 315, "height": 313 },
			"1/1/0004": { "x": 5.25, "y": 13.12, "width": 315, "height": 313 },
			"1/1/0005": { "x": 5.25, "y": 13.12, "width": 315, "height": 313 },
			"1/1/0007": { "x": 5.25, "y": 13.12, "width": 315, "height": 313 },
			"1/1/0009": { "x": 5.25, "y": 13.12, "width": 315, "height": 313 }
		},
		"1/2": {
			"1/1": { "x": 1.34, "y": 29.66, "width": 129, "height": 82 }
		},
		"1/3": {
			"1/1": { "x": 1.34, "y": 29.66, "width": 129, "height": 82 }
		},
		"1/4": {
			"1/1": { "x": 1.34, "y": 29.66, "width": 129, "height": 82 }
		},
		"1/5": {
			"1/1": { "x": 1.34, "y": 29.66, "width": 129, "height": 82 }
		}
	}
},
"animations": {
	"animation": {
		"slots": {
			"1/000000": {
				"attachment": [
					{ "time": 0, "name": null },
					{ "time": 0.0333, "name": "1/000000" },
					{ "time": 0.1, "name": "1/000002" },
					{ "time": 0.1666, "name": "1/000004" },
					{ "time": 0.2333, "name": "1/000006" },
					{ "time": 0.3, "name": "1/000008" },
					{ "time": 0.3666, "name": "1/000010" },
					{ "time": 0.4333, "name": "1/000012" },
					{ "time": 0.5, "name": "1/000014" },
					{ "time": 0.5666, "name": "1/000016" },
					{ "time": 0.6333, "name": null }
				]
			},
			"1/1": {
				"attachment": [
					{ "time": 0, "name": null },
					{ "time": 0.0333, "name": "1/1" }
				],
				"color": [
					{ "time": 0, "color": "ffffffff", "curve": "stepped" },
					{ "time": 0.3666, "color": "ffffffff" },
					{ "time": 0.5333, "color": "ffffff00" }
				]
			},
			"1/2": {
				"attachment": [
					{ "time": 0, "name": null },
					{ "time": 0.0333, "name": "1/1" }
				],
				"color": [
					{ "time": 0, "color": "ffffffff", "curve": "stepped" },
					{ "time": 0.3666, "color": "ffffffff" },
					{ "time": 0.5333, "color": "ffffff00" }
				]
			},
			"1/3": {
				"attachment": [
					{ "time": 0, "name": null },
					{ "time": 0.0333, "name": "1/1" }
				],
				"color": [
					{ "time": 0, "color": "ffffffff", "curve": "stepped" },
					{ "time": 0.3666, "color": "ffffffff" },
					{ "time": 0.5333, "color": "ffffff00" }
				]
			},
			"1/4": {
				"attachment": [
					{ "time": 0, "name": null },
					{ "time": 0.0333, "name": "1/1" }
				],
				"color": [
					{ "time": 0, "color": "ffffffff", "curve": "stepped" },
					{ "time": 0.3666, "color": "ffffffff" },
					{ "time": 0.5333, "color": "ffffff00" }
				]
			},
			"1/5": {
				"attachment": [
					{ "time": 0, "name": null },
					{ "time": 0.0333, "name": "1/1" }
				],
				"color": [
					{ "time": 0, "color": "ffffffff", "curve": "stepped" },
					{ "time": 0.3666, "color": "ffffffff" },
					{ "time": 0.5333, "color": "ffffff00" }
				]
			},
			"1/1/0001": {
				"attachment": [
					{ "time": 0, "name": null },
					{ "time": 0.4666, "name": "1/1/0001" },
					{ "time": 0.5333, "name": "1/1/0002" },
					{ "time": 0.6, "name": "1/1/0003" },
					{ "time": 0.6666, "name": "1/1/0004" },
					{ "time": 0.7333, "name": "1/1/0005" },
					{ "time": 0.8, "name": "1/1/0007" },
					{ "time": 0.8666, "name": "1/1/0009" },
					{ "time": 0.9333, "name": null }
				]
			}
		},
		"bones": {
			"bone": {
				"rotate": [
					{ "time": 0, "angle": 0, "curve": "stepped" },
					{ "time": 0.0333, "angle": 0 }
				],
				"translate": [
					{ "time": 0, "x": -72.02, "y": 0 },
					{ "time": 0.0333, "x": -391.87, "y": -27.7 },
					{ "time": 0.4333, "x": 15.51, "y": -27.7 },
					{ "time": 0.5333, "x": 134.06, "y": -27.7 }
				],
				"scale": [
					{ "time": 0, "x": 1, "y": 1, "curve": "stepped" },
					{ "time": 0.0333, "x": 1, "y": 1 }
				]
			},
			"bone2": {
				"translate": [
					{ "time": 0, "x": 0, "y": -8.09 },
					{ "time": 0.0333, "x": 0, "y": -16.19 }
				]
			},
			"bone3": {
				"translate": [
					{ "time": 0, "x": 0, "y": -8.09 },
					{ "time": 0.0333, "x": 0, "y": -16.19 }
				]
			},
			"bone4": {
				"translate": [
					{ "time": 0, "x": 0, "y": -8.09 },
					{ "time": 0.0333, "x": 0, "y": -16.19 }
				]
			},
			"bone5": {
				"translate": [
					{ "time": 0, "x": 0, "y": -8.09 },
					{ "time": 0.0333, "x": 0, "y": -16.19 }
				]
			},
			"bone7": {
				"rotate": [
					{ "time": 0, "angle": 0 }
				],
				"translate": [
					{ "time": 0, "x": -318.83, "y": -1.4 },
					{ "time": 0.0333, "x": -450.59, "y": -1.4 },
					{ "time": 0.4333, "x": -62.88, "y": -1.4 },
					{ "time": 0.5333, "x": 55.66, "y": -1.4 }
				],
				"scale": [
					{ "time": 0, "x": 1, "y": 1 }
				]
			},
			"bone9": {
				"rotate": [
					{ "time": 0, "angle": 0 }
				],
				"translate": [
					{ "time": 0, "x": 98.26, "y": -41.61, "curve": "stepped" },
					{ "time": 0.4666, "x": 98.26, "y": -41.61 }
				],
				"scale": [
					{ "time": 0, "x": 1, "y": 1 }
				]
			}
		}
	}
}
}